octo_pipeline_python/backends/golang/__init__.py
octo_pipeline_python/backends/golang/golang_backend.py
octo_pipeline_python/backends/golang/actions/__init__.py
octo_pipeline_python/backends/golang/actions/golang_build.py
octo_pipeline_python/backends/golang/actions/golang_lint_checks.py
octo_pipeline_python/backends/golang/actions/golang_unit_tests.py
octo_pipeline_python/backends/golang/models/__init__.py
octo_pipeline_python/backends/golang/models/golang_model.py
octo_pipeline_backend_golang_python-1.3.2.dist-info/LICENSE.txt
octo_pipeline_backend_golang_python-1.3.2.dist-info/METADATA
octo_pipeline_backend_golang_python-1.3.2.dist-info/README.md
octo_pipeline_backend_golang_python-1.3.2.dist-info/WHEEL
octo_pipeline_backend_golang_python-1.3.2.dist-info/top_level.txt
octo_pipeline_backend_golang_python-1.3.2.dist-info/RECORD
